lightSOM/__init__.py
lightSOM/decay_functions.py
lightSOM/distance.py
lightSOM/hexagons.py
lightSOM/neighborhood.py
lightSOM/nodes.py
lightSOM/normalization.py
lightSOM/som_net.py
lightSOM/version.py
lightSOM/clustering/__init__.py
lightSOM/clustering/densityPeak.py
lightSOM/clustering/qualityThreshold.py
lightSOM/visualization/__init__.py
lightSOM/visualization/map_plot.py
lightSOM/visualization/resources.py
lightSOM/visualization/som_view.py
lightSOM-1.5.0.dist-info/METADATA
lightSOM-1.5.0.dist-info/WHEEL
lightSOM-1.5.0.dist-info/top_level.txt
lightSOM-1.5.0.dist-info/RECORD
