Metadata-Version: 2.1
Name: lightSOM
Version: 1.5.0
Summary: Self Organizing Maps Package
Home-page: UNKNOWN
Author: Vahid Moosavi and Sebastian Packmann
License: UNKNOWN
Platform: UNKNOWN
Classifier: Programming Language :: Python :: 3.7
Classifier: Operating System :: OS Independent
Classifier: Development Status :: 4 - Beta
Requires-Python: >=3.7
Requires-Dist: numpy (>=1.7)
Requires-Dist: scipy (>=0.9)
Requires-Dist: scikit-learn (>=0.21)
Requires-Dist: numexpr (>=2.5)
